metarag/__init__.py
metarag/aggregator.py
metarag/cli.py
metarag/config.py
metarag/core.py
metarag/document_loader.py
metarag/llm_interface.py
metarag/response_ranker.py
metarag/utils.py
metarag-0.1.7.dist-info/METADATA
metarag-0.1.7.dist-info/WHEEL
metarag-0.1.7.dist-info/entry_points.txt
metarag-0.1.7.dist-info/top_level.txt
metarag-0.1.7.dist-info/RECORD
