Metadata-Version: 2.1
Name: metarag
Version: 0.1.7
Summary: MetaRAG: A multi-LLM ensemble Retrieval-Augmented Generation framework with cosine similarity ranking.
Author: Nisharg Nargund
Author-email: nisarg.nargund@gmail.com
Keywords: llm,retrieval,augmented,generation,ai,nlp
Classifier: Programming Language :: Python :: 3
Classifier: License :: OSI Approved :: MIT License
Classifier: Operating System :: OS Independent
Classifier: Development Status :: 4 - Beta
Classifier: Intended Audience :: Developers
Classifier: Intended Audience :: Science/Research
Classifier: Topic :: Scientific/Engineering :: Artificial Intelligence
Requires-Python: >=3.8
Requires-Dist: langchain
Requires-Dist: langchain-groq
Requires-Dist: sentence-transformers
Requires-Dist: faiss-cpu
Requires-Dist: numpy
Requires-Dist: PyPDF2
Requires-Dist: scikit-learn
Requires-Dist: langchain-community
